suaidoc/__init__.py
suaidoc/suaidoc.py
suaidoc/scripts/__init__.py
suaidoc/scripts/replace.py
suaidoc/scripts/update_md.py
suaidoc/templates/__init__.py
suaidoc/templates/template.html
suaidoc/templates/template.tex
suaidoc-0.2.5.dist-info/METADATA
suaidoc-0.2.5.dist-info/WHEEL
suaidoc-0.2.5.dist-info/entry_points.txt
suaidoc-0.2.5.dist-info/top_level.txt
suaidoc-0.2.5.dist-info/RECORD
