Metadata-Version: 2.1
Name: suaidoc
Version: 0.2.5
Summary: CLI for generating reports from Markodwn according to GOST 7.32
Author-email: Vlad Vorobew <razrab.ytka@gmail.com>
Maintainer-email: Vlad Vorobew <razrab.ytka@gmail.com>
License: MIT License
Project-URL: Homepage, https://github.com/vladcto/suaidoc
Project-URL: Repository, https://github.com/vladcto/suaidoc.git
Project-URL: Issues, https://github.com/vladcto/suaidoc/issues
Project-URL: Changelog, https://github.com/vladcto/suaidoc/blob/main/CHANGELOG.md
Keywords: cli,university,gost,docs,pdf,generating,suai
Classifier: Development Status :: 4 - Beta
Classifier: Environment :: Console
Classifier: Intended Audience :: Education
Classifier: License :: OSI Approved :: MIT License
Classifier: Programming Language :: Python
Classifier: Topic :: Utilities
Classifier: Topic :: Text Processing :: Markup :: Markdown
Classifier: Topic :: Software Development :: Documentation
Requires-Dist: click
Requires-Dist: pdfkit
Requires-Dist: python-frontmatter
